jupyter2pytest/__init__.py
jupyter2pytest/__main__.py
jupyter2pytest/compiler.py
jupyter2pytest/extractor.py
jupyter2pytest/test_code_block_template.py.template
jupyter2pytest/test_file_template.py.template
jupyter2pytest/test_function_template.py.template
jupyter2pytest-0.3.4.dist-info/LICENSE
jupyter2pytest-0.3.4.dist-info/METADATA
jupyter2pytest-0.3.4.dist-info/WHEEL
jupyter2pytest-0.3.4.dist-info/top_level.txt
jupyter2pytest-0.3.4.dist-info/RECORD
