Metadata-Version: 2.2
Name: jupyter2pytest
Version: 0.3.4
Summary: Converts Jupyter notebooks into pytest capable test files.
Author-email: Garrett Credi <garrettcredi@gmail.com>
License: MIT License
Project-URL: Homepage, https://github.com/dsdiscovery/jupyter2pytest
Project-URL: Repository, https://github.com/dsdiscovery/jupyter2pytest
Keywords: pytest,jupyter,autograding
Classifier: Development Status :: 4 - Beta
Classifier: Environment :: Console
Classifier: Operating System :: OS Independent
Classifier: Programming Language :: Python :: 3
Classifier: Topic :: Software Development :: Testing
Classifier: Topic :: Education
Classifier: Typing :: Typed
Requires-Python: >=3.6
License-File: LICENSE
Requires-Dist: nbformat
Requires-Dist: tblib
